{
  "date": "2026-02-22",
  "sessions": [
    {
      "facility": "Eileen Dailly Leisure Pool",
      "city": "Burnaby",
      "address": "240 Willingdon Ave, Burnaby, BC V5C 5E9",
      "lat": 49.28379,
      "lng": -122.97858,
      "date": "2026-02-22",
      "startTime": "06:00",
      "endTime": "07:00",
      "type": "Lap Swim",
      "activityName": "Lap Swim",
      "ageRange": "4 lanes",
      "activityUrl": "https://www.burnaby.ca/recreation-and-arts/activities-and-registration/daily-activities?activity_tid=651&location_ref=3041",
      "facilityUrl": "https://www.burnaby.ca/recreation-and-arts/recreation-facilities/eileen-dailly-leisure-pool-and-fitness-centre",
      "scheduleUrl": "https://www.burnaby.ca/recreation-and-arts/activities-and-registration/daily-activities?activity_tid=651&location_ref=3041"
    },
    {
      "facility": "Walnut Grove Community Centre",
      "city": "Langley",
      "address": "8889 Walnut Grove Drive, Langley, BC",
      "lat": 49.1635264,
      "lng": -122.6415541,
      "date": "2026-02-22",
      "startTime": "06:00",
      "endTime": "08:00",
      "type": "Lap Swim",
      "activityName": "Lap Swim - Short Course (25m)",
      "activityUrl": "https://tol.perfectmind.com/23784/Clients/BookMe4?widgetId=67fd560e-f1ae-449f-a666-3edbcfd93783",
      "facilityUrl": "https://www.tol.ca/recreation-culture/recreation-facilities/walnut-grove-community-centre/",
      "scheduleUrl": "https://www.tol.ca/recreation-culture/recreation-facilities/walnut-grove-community-centre/"
    },
    {
      "facility": "Eileen Dailly Leisure Pool",
      "city": "Burnaby",
      "address": "240 Willingdon Ave, Burnaby, BC V5C 5E9",
      "lat": 49.28379,
      "lng": -122.97858,
      "date": "2026-02-22",
      "startTime": "07:00",
      "endTime": "09:00",
      "type": "Lap Swim",
      "activityName": "Lap Swim",
      "ageRange": "2 lanes",
      "activityUrl": "https://www.burnaby.ca/recreation-and-arts/activities-and-registration/daily-activities?activity_tid=651&location_ref=3041",
      "facilityUrl": "https://www.burnaby.ca/recreation-and-arts/recreation-facilities/eileen-dailly-leisure-pool-and-fitness-centre",
      "scheduleUrl": "https://www.burnaby.ca/recreation-and-arts/activities-and-registration/daily-activities?activity_tid=651&location_ref=3041"
    },
    {
      "facility": "Edmonds Community Centre",
      "city": "Burnaby",
      "address": "7433 Edmonds St, Burnaby, BC V3N 1B1",
      "lat": 49.21248,
      "lng": -122.95865,
      "date": "2026-02-22",
      "startTime": "08:00",
      "endTime": "12:00",
      "type": "Lessons",
      "activityName": "Lessons & Leisure Swim",
      "ageRange": null,
      "activityUrl": "https://www.burnaby.ca/recreation-and-arts/activities-and-registration/daily-activities?activity_tid=651&location_ref=2336",
      "facilityUrl": "https://www.burnaby.ca/recreation-and-arts/recreation-facilities/edmonds-community-centre",
      "scheduleUrl": "https://www.burnaby.ca/recreation-and-arts/activities-and-registration/daily-activities?activity_tid=651&location_ref=2336"
    },
    {
      "facility": "Walnut Grove Community Centre",
      "city": "Langley",
      "address": "8889 Walnut Grove Drive, Langley, BC",
      "lat": 49.1635264,
      "lng": -122.6415541,
      "date": "2026-02-22",
      "startTime": "08:00",
      "endTime": "10:00",
      "type": "Family Swim",
      "activityName": "Adult and Tot Swim",
      "activityUrl": "https://tol.perfectmind.com/23784/Clients/BookMe4?widgetId=67fd560e-f1ae-449f-a666-3edbcfd93783",
      "facilityUrl": "https://www.tol.ca/recreation-culture/recreation-facilities/walnut-grove-community-centre/",
      "scheduleUrl": "https://www.tol.ca/recreation-culture/recreation-facilities/walnut-grove-community-centre/"
    },
    {
      "facility": "W.C. Blair Recreation Centre",
      "city": "Langley",
      "address": "22200 Fraser Highway, Langley, BC",
      "lat": 49.0913815,
      "lng": -122.6096282,
      "date": "2026-02-22",
      "startTime": "08:00",
      "endTime": "21:00",
      "type": "Public Swim",
      "activityName": "Pool Closure - Annual Maintenance",
      "activityUrl": "https://tol.perfectmind.com/23784/Clients/BookMe4?widgetId=67fd560e-f1ae-449f-a666-3edbcfd93783",
      "facilityUrl": "https://www.tol.ca/recreation-culture/recreation-facilities/wc-blair-recreation-centre/",
      "scheduleUrl": "https://www.tol.ca/recreation-culture/recreation-facilities/wc-blair-recreation-centre/"
    },
    {
      "facility": "Eileen Dailly Leisure Pool",
      "city": "Burnaby",
      "address": "240 Willingdon Ave, Burnaby, BC V5C 5E9",
      "lat": 49.28379,
      "lng": -122.97858,
      "date": "2026-02-22",
      "startTime": "09:00",
      "endTime": "13:00",
      "type": "Lessons",
      "activityName": "Swim Lessons Only",
      "ageRange": null,
      "activityUrl": "https://www.burnaby.ca/recreation-and-arts/activities-and-registration/daily-activities?activity_tid=651&location_ref=3041",
      "facilityUrl": "https://www.burnaby.ca/recreation-and-arts/recreation-facilities/eileen-dailly-leisure-pool-and-fitness-centre",
      "scheduleUrl": "https://www.burnaby.ca/recreation-and-arts/activities-and-registration/daily-activities?activity_tid=651&location_ref=3041"
    },
    {
      "facility": "Bonsor Recreation Complex",
      "city": "Burnaby",
      "address": "6550 Bonsor Ave, Burnaby, BC V5H 3G4",
      "lat": 49.22887,
      "lng": -122.99389,
      "date": "2026-02-22",
      "startTime": "10:00",
      "endTime": "11:00",
      "type": "Aquafit",
      "activityName": "Aquafit",
      "ageRange": null,
      "activityUrl": "https://www.burnaby.ca/recreation-and-arts/activities-and-registration/daily-activities?activity_tid=651&location_ref=2996",
      "facilityUrl": "https://www.burnaby.ca/recreation-and-arts/recreation-facilities/bonsor-recreation-complex",
      "scheduleUrl": "https://www.burnaby.ca/recreation-and-arts/activities-and-registration/daily-activities?activity_tid=651&location_ref=2996"
    },
    {
      "facility": "Aldergrove Community Centre",
      "city": "Langley",
      "address": "27032 Fraser Highway, Langley, BC",
      "lat": 49.1125355,
      "lng": -122.6766332,
      "date": "2026-02-22",
      "startTime": "10:00",
      "endTime": "13:00",
      "type": "Lessons",
      "activityName": "Lessons and Limited Lap Swim",
      "activityUrl": "https://tol.perfectmind.com/23784/Clients/BookMe4?widgetId=67fd560e-f1ae-449f-a666-3edbcfd93783",
      "facilityUrl": "https://www.tol.ca/recreation-culture/recreation-facilities/aldergrove-credit-union-community-centre/",
      "scheduleUrl": "https://www.tol.ca/recreation-culture/recreation-facilities/aldergrove-credit-union-community-centre/"
    },
    {
      "facility": "Walnut Grove Community Centre",
      "city": "Langley",
      "address": "8889 Walnut Grove Drive, Langley, BC",
      "lat": 49.1635264,
      "lng": -122.6415541,
      "date": "2026-02-22",
      "startTime": "10:00",
      "endTime": "17:00",
      "type": "Public Swim",
      "activityName": "Public Swim",
      "activityUrl": "https://tol.perfectmind.com/23784/Clients/BookMe4?widgetId=67fd560e-f1ae-449f-a666-3edbcfd93783",
      "facilityUrl": "https://www.tol.ca/recreation-culture/recreation-facilities/walnut-grove-community-centre/",
      "scheduleUrl": "https://www.tol.ca/recreation-culture/recreation-facilities/walnut-grove-community-centre/"
    },
    {
      "facility": "Edmonds Community Centre",
      "city": "Burnaby",
      "address": "7433 Edmonds St, Burnaby, BC V3N 1B1",
      "lat": 49.21248,
      "lng": -122.95865,
      "date": "2026-02-22",
      "startTime": "12:00",
      "endTime": "18:00",
      "type": "Public Swim",
      "activityName": "Public Swim",
      "ageRange": null,
      "activityUrl": "https://www.burnaby.ca/recreation-and-arts/activities-and-registration/daily-activities?activity_tid=651&location_ref=2336",
      "facilityUrl": "https://www.burnaby.ca/recreation-and-arts/recreation-facilities/edmonds-community-centre",
      "scheduleUrl": "https://www.burnaby.ca/recreation-and-arts/activities-and-registration/daily-activities?activity_tid=651&location_ref=2336"
    },
    {
      "facility": "Edmonds Community Centre",
      "city": "Burnaby",
      "address": "7433 Edmonds St, Burnaby, BC V3N 1B1",
      "lat": 49.21248,
      "lng": -122.95865,
      "date": "2026-02-22",
      "startTime": "12:30",
      "endTime": "14:30",
      "type": "Public Swim",
      "activityName": "Slide",
      "ageRange": null,
      "activityUrl": "https://www.burnaby.ca/recreation-and-arts/activities-and-registration/daily-activities?activity_tid=651&location_ref=2336",
      "facilityUrl": "https://www.burnaby.ca/recreation-and-arts/recreation-facilities/edmonds-community-centre",
      "scheduleUrl": "https://www.burnaby.ca/recreation-and-arts/activities-and-registration/daily-activities?activity_tid=651&location_ref=2336"
    },
    {
      "facility": "Bonsor Recreation Complex",
      "city": "Burnaby",
      "address": "6550 Bonsor Ave, Burnaby, BC V5H 3G4",
      "lat": 49.22887,
      "lng": -122.99389,
      "date": "2026-02-22",
      "startTime": "13:00",
      "endTime": "17:00",
      "type": "Family Swim",
      "activityName": "Family Swim",
      "ageRange": "No lap lanes",
      "activityUrl": "https://www.burnaby.ca/recreation-and-arts/activities-and-registration/daily-activities?activity_tid=651&location_ref=2996",
      "facilityUrl": "https://www.burnaby.ca/recreation-and-arts/recreation-facilities/bonsor-recreation-complex",
      "scheduleUrl": "https://www.burnaby.ca/recreation-and-arts/activities-and-registration/daily-activities?activity_tid=651&location_ref=2996"
    },
    {
      "facility": "Eileen Dailly Leisure Pool",
      "city": "Burnaby",
      "address": "240 Willingdon Ave, Burnaby, BC V5C 5E9",
      "lat": 49.28379,
      "lng": -122.97858,
      "date": "2026-02-22",
      "startTime": "13:00",
      "endTime": "16:00",
      "type": "Family Swim",
      "activityName": "Family Swim",
      "ageRange": null,
      "activityUrl": "https://www.burnaby.ca/recreation-and-arts/activities-and-registration/daily-activities?activity_tid=651&location_ref=3041",
      "facilityUrl": "https://www.burnaby.ca/recreation-and-arts/recreation-facilities/eileen-dailly-leisure-pool-and-fitness-centre",
      "scheduleUrl": "https://www.burnaby.ca/recreation-and-arts/activities-and-registration/daily-activities?activity_tid=651&location_ref=3041"
    },
    {
      "facility": "Aldergrove Community Centre",
      "city": "Langley",
      "address": "27032 Fraser Highway, Langley, BC",
      "lat": 49.1125355,
      "lng": -122.6766332,
      "date": "2026-02-22",
      "startTime": "13:00",
      "endTime": "20:00",
      "type": "Public Swim",
      "activityName": "Public Swim",
      "activityUrl": "https://tol.perfectmind.com/23784/Clients/BookMe4?widgetId=67fd560e-f1ae-449f-a666-3edbcfd93783",
      "facilityUrl": "https://www.tol.ca/recreation-culture/recreation-facilities/aldergrove-credit-union-community-centre/",
      "scheduleUrl": "https://www.tol.ca/recreation-culture/recreation-facilities/aldergrove-credit-union-community-centre/"
    },
    {
      "facility": "Edmonds Community Centre",
      "city": "Burnaby",
      "address": "7433 Edmonds St, Burnaby, BC V3N 1B1",
      "lat": 49.21248,
      "lng": -122.95865,
      "date": "2026-02-22",
      "startTime": "15:30",
      "endTime": "17:30",
      "type": "Public Swim",
      "activityName": "Slide",
      "ageRange": null,
      "activityUrl": "https://www.burnaby.ca/recreation-and-arts/activities-and-registration/daily-activities?activity_tid=651&location_ref=2336",
      "facilityUrl": "https://www.burnaby.ca/recreation-and-arts/recreation-facilities/edmonds-community-centre",
      "scheduleUrl": "https://www.burnaby.ca/recreation-and-arts/activities-and-registration/daily-activities?activity_tid=651&location_ref=2336"
    },
    {
      "facility": "Eileen Dailly Leisure Pool",
      "city": "Burnaby",
      "address": "240 Willingdon Ave, Burnaby, BC V5C 5E9",
      "lat": 49.28379,
      "lng": -122.97858,
      "date": "2026-02-22",
      "startTime": "16:00",
      "endTime": "20:00",
      "type": "Public Swim",
      "activityName": "Public Swim",
      "ageRange": null,
      "activityUrl": "https://www.burnaby.ca/recreation-and-arts/activities-and-registration/daily-activities?activity_tid=651&location_ref=3041",
      "facilityUrl": "https://www.burnaby.ca/recreation-and-arts/recreation-facilities/eileen-dailly-leisure-pool-and-fitness-centre",
      "scheduleUrl": "https://www.burnaby.ca/recreation-and-arts/activities-and-registration/daily-activities?activity_tid=651&location_ref=3041"
    },
    {
      "facility": "Walnut Grove Community Centre",
      "city": "Langley",
      "address": "8889 Walnut Grove Drive, Langley, BC",
      "lat": 49.1635264,
      "lng": -122.6415541,
      "date": "2026-02-22",
      "startTime": "17:00",
      "endTime": "21:00",
      "type": "Lessons",
      "activityName": "Lessons and Limited Lap Swim",
      "activityUrl": "https://tol.perfectmind.com/23784/Clients/BookMe4?widgetId=67fd560e-f1ae-449f-a666-3edbcfd93783",
      "facilityUrl": "https://www.tol.ca/recreation-culture/recreation-facilities/walnut-grove-community-centre/",
      "scheduleUrl": "https://www.tol.ca/recreation-culture/recreation-facilities/walnut-grove-community-centre/"
    },
    {
      "facility": "Edmonds Community Centre",
      "city": "Burnaby",
      "address": "7433 Edmonds St, Burnaby, BC V3N 1B1",
      "lat": 49.21248,
      "lng": -122.95865,
      "date": "2026-02-22",
      "startTime": "18:00",
      "endTime": "20:00",
      "type": "Public Swim",
      "activityName": "Leisure Pool Only Swim",
      "ageRange": null,
      "activityUrl": "https://www.burnaby.ca/recreation-and-arts/activities-and-registration/daily-activities?activity_tid=651&location_ref=2336",
      "facilityUrl": "https://www.burnaby.ca/recreation-and-arts/recreation-facilities/edmonds-community-centre",
      "scheduleUrl": "https://www.burnaby.ca/recreation-and-arts/activities-and-registration/daily-activities?activity_tid=651&location_ref=2336"
    },
    {
      "facility": "Bonsor Recreation Complex",
      "city": "Burnaby",
      "address": "6550 Bonsor Ave, Burnaby, BC V5H 3G4",
      "lat": 49.22887,
      "lng": -122.99389,
      "date": "2026-02-22",
      "startTime": "19:00",
      "endTime": "20:00",
      "type": "Lap Swim",
      "activityName": "Lap Swim",
      "ageRange": "No shallow end",
      "activityUrl": "https://www.burnaby.ca/recreation-and-arts/activities-and-registration/daily-activities?activity_tid=651&location_ref=2996",
      "facilityUrl": "https://www.burnaby.ca/recreation-and-arts/recreation-facilities/bonsor-recreation-complex",
      "scheduleUrl": "https://www.burnaby.ca/recreation-and-arts/activities-and-registration/daily-activities?activity_tid=651&location_ref=2996"
    },
    {
      "facility": "Bonsor Recreation Complex",
      "city": "Burnaby",
      "address": "6550 Bonsor Ave, Burnaby, BC V5H 3G4",
      "lat": 49.22887,
      "lng": -122.99389,
      "date": "2026-02-22",
      "startTime": "20:00",
      "endTime": "21:00",
      "type": "Lap Swim",
      "activityName": "Lap Swim",
      "ageRange": null,
      "activityUrl": "https://www.burnaby.ca/recreation-and-arts/activities-and-registration/daily-activities?activity_tid=651&location_ref=2996",
      "facilityUrl": "https://www.burnaby.ca/recreation-and-arts/recreation-facilities/bonsor-recreation-complex",
      "scheduleUrl": "https://www.burnaby.ca/recreation-and-arts/activities-and-registration/daily-activities?activity_tid=651&location_ref=2996"
    },
    {
      "facility": "Edmonds Community Centre",
      "city": "Burnaby",
      "address": "7433 Edmonds St, Burnaby, BC V3N 1B1",
      "lat": 49.21248,
      "lng": -122.95865,
      "date": "2026-02-22",
      "startTime": "20:00",
      "endTime": "21:00",
      "type": "Lap Swim",
      "activityName": "Lap Swim",
      "ageRange": "4 lanes",
      "activityUrl": "https://www.burnaby.ca/recreation-and-arts/activities-and-registration/daily-activities?activity_tid=651&location_ref=2336",
      "facilityUrl": "https://www.burnaby.ca/recreation-and-arts/recreation-facilities/edmonds-community-centre",
      "scheduleUrl": "https://www.burnaby.ca/recreation-and-arts/activities-and-registration/daily-activities?activity_tid=651&location_ref=2336"
    },
    {
      "facility": "Eileen Dailly Leisure Pool",
      "city": "Burnaby",
      "address": "240 Willingdon Ave, Burnaby, BC V5C 5E9",
      "lat": 49.28379,
      "lng": -122.97858,
      "date": "2026-02-22",
      "startTime": "20:00",
      "endTime": "21:00",
      "type": "Lap Swim",
      "activityName": "Lap Swim",
      "ageRange": "4 lanes",
      "activityUrl": "https://www.burnaby.ca/recreation-and-arts/activities-and-registration/daily-activities?activity_tid=651&location_ref=3041",
      "facilityUrl": "https://www.burnaby.ca/recreation-and-arts/recreation-facilities/eileen-dailly-leisure-pool-and-fitness-centre",
      "scheduleUrl": "https://www.burnaby.ca/recreation-and-arts/activities-and-registration/daily-activities?activity_tid=651&location_ref=3041"
    }
  ],
  "count": 23
}