{
  "date": "2026-03-04",
  "sessions": [
    {
      "facility": "Vancouver Aquatic Centre",
      "city": "Vancouver",
      "address": "1050 Beach Ave, Vancouver, BC V6E 1T7",
      "lat": 49.2777,
      "lng": -123.1394,
      "date": "2026-03-04",
      "startTime": "09:20",
      "endTime": "10:15",
      "type": "Aquafit",
      "activityName": "Aquafit - Shallow Water Moderate",
      "description": "This 55-minute Aquafit class is a moderately paced and energizing class that utilizes water resistance for a variety of exercise combinations with warm up, cardio, strength, stretch and cool down com",
      "ageRange": "",
      "activityUrl": "https://ca.apm.activecommunities.com/vancouver/Activity_Search/aquafit---shallow-water-moderate/599144",
      "eventItemId": 599144
    }
  ],
  "count": 1
}